<mesh>
	<submeshes>
		<submesh material="Dirtmap" usesharedvertices="false">
			<faces count="83">
				<face v1="0" v2="1" v3="2"/>
				<face v1="1" v2="3" v3="2"/>
				<face v1="4" v2="5" v3="6"/>
				<face v1="5" v2="7" v3="6"/>
				<face v1="7" v2="8" v3="6"/>
				<face v1="7" v2="9" v3="10"/>
				<face v1="7" v2="10" v3="8"/>
				<face v1="9" v2="11" v3="10"/>
				<face v1="12" v2="13" v3="14"/>
				<face v1="15" v2="16" v3="18"/>
				<face v1="16" v2="17" v3="18"/>
				<face v1="19" v2="20" v3="22"/>
				<face v1="20" v2="21" v3="22"/>
				<face v1="23" v2="24" v3="26"/>
				<face v1="24" v2="25" v3="26"/>
				<face v1="27" v2="28" v3="29"/>
				<face v1="27" v2="29" v3="30"/>
				<face v1="31" v2="32" v3="33"/>
				<face v1="31" v2="33" v3="34"/>
				<face v1="35" v2="36" v3="37"/>
				<face v1="35" v2="37" v3="38"/>
				<face v1="39" v2="40" v3="41"/>
				<face v1="42" v2="43" v3="44"/>
				<face v1="45" v2="46" v3="48"/>
				<face v1="46" v2="47" v3="48"/>
				<face v1="49" v2="50" v3="52"/>
				<face v1="50" v2="51" v3="52"/>
				<face v1="53" v2="54" v3="55"/>
				<face v1="53" v2="55" v3="56"/>
				<face v1="57" v2="58" v3="59"/>
				<face v1="57" v2="59" v3="60"/>
				<face v1="61" v2="62" v3="63"/>
				<face v1="64" v2="65" v3="66"/>
				<face v1="67" v2="68" v3="69"/>
				<face v1="70" v2="71" v3="72"/>
				<face v1="73" v2="74" v3="75"/>
				<face v1="76" v2="77" v3="78"/>
				<face v1="77" v2="79" v3="78"/>
				<face v1="79" v2="80" v3="78"/>
				<face v1="79" v2="81" v3="82"/>
				<face v1="79" v2="82" v3="80"/>
				<face v1="81" v2="83" v3="82"/>
				<face v1="84" v2="85" v3="86"/>
				<face v1="87" v2="88" v3="90"/>
				<face v1="88" v2="89" v3="90"/>
				<face v1="91" v2="92" v3="94"/>
				<face v1="92" v2="93" v3="94"/>
				<face v1="95" v2="96" v3="98"/>
				<face v1="96" v2="97" v3="98"/>
				<face v1="99" v2="100" v3="101"/>
				<face v1="99" v2="101" v3="102"/>
				<face v1="103" v2="104" v3="105"/>
				<face v1="103" v2="105" v3="106"/>
				<face v1="107" v2="108" v3="109"/>
				<face v1="107" v2="109" v3="110"/>
				<face v1="111" v2="112" v3="113"/>
				<face v1="114" v2="115" v3="116"/>
				<face v1="117" v2="118" v3="120"/>
				<face v1="118" v2="119" v3="120"/>
				<face v1="121" v2="122" v3="124"/>
				<face v1="122" v2="123" v3="124"/>
				<face v1="125" v2="126" v3="127"/>
				<face v1="125" v2="127" v3="128"/>
				<face v1="129" v2="130" v3="131"/>
				<face v1="129" v2="131" v3="132"/>
				<face v1="133" v2="134" v3="135"/>
				<face v1="136" v2="137" v3="138"/>
				<face v1="139" v2="140" v3="142"/>
				<face v1="140" v2="141" v3="142"/>
				<face v1="143" v2="144" v3="145"/>
				<face v1="143" v2="145" v3="146"/>
				<face v1="147" v2="148" v3="149"/>
				<face v1="150" v2="151" v3="153"/>
				<face v1="151" v2="152" v3="153"/>
				<face v1="154" v2="155" v3="156"/>
				<face v1="154" v2="156" v3="157"/>
				<face v1="158" v2="159" v3="160"/>
				<face v1="80" v2="158" v3="160"/>
				<face v1="161" v2="158" v3="80"/>
				<face v1="162" v2="163" v3="164"/>
				<face v1="162" v2="164" v3="165"/>
				<face v1="8" v2="162" v3="165"/>
				<face v1="166" v2="162" v3="8"/>
			</faces>
			<geometry vertexcount="167">
				<vertexbuffer positions="true" normals="true" texture_coords="1">
					<vertex>
						<position x="242.682999" y="-100.000000" z="517.911011"/>
						<normal x="0.000000" y="1.000000" z="0.000000"/>
						<texcoord u="0.000000" v="0.983600"/>
					</vertex>
					<vertex>
						<position x="243.261002" y="-100.000000" z="519.125977"/>
						<normal x="0.000000" y="1.000000" z="0.000000"/>
						<texcoord u="0.224200" v="0.983600"/>
					</vertex>
					<vertex>
						<position x="243.352005" y="-100.000000" z="519.090027"/>
						<normal x="0.000000" y="1.000000" z="0.000000"/>
						<texcoord u="0.225400" v="1.000000"/>
					</vertex>
					<vertex>
						<position x="243.656998" y="-100.000000" z="520.411011"/>
						<normal x="-0.000000" y="1.000000" z="0.000000"/>
						<texcoord u="0.446100" v="0.951300"/>
					</vertex>
					<vertex>
						<position x="-2460.414063" y="-23.941000" z="-2800.092041"/>
						<normal x="0.000000" y="1.000000" z="0.000000"/>
						<texcoord u="0.502700" v="-2.794700"/>
					</vertex>
					<vertex>
						<position x="-2459.346924" y="-23.941000" z="-2799.896973"/>
						<normal x="0.000000" y="1.000000" z="0.000000"/>
						<texcoord u="0.682800" v="-2.809000"/>
					</vertex>
					<vertex>
						<position x="-2459.324951" y="-23.941000" z="-2799.980957"/>
						<normal x="0.000000" y="1.000000" z="0.000000"/>
						<texcoord u="0.685100" v="-2.794700"/>
					</vertex>
					<vertex>
						<position x="-2458.324951" y="-23.941000" z="-2799.537109"/>
						<normal x="0.000000" y="1.000000" z="0.000000"/>
						<texcoord u="0.858400" v="-2.851300"/>
					</vertex>
					<vertex>
						<position x="-2458.179932" y="-23.941000" z="-2799.864014"/>
						<normal x="0.000000" y="1.000000" z="0.000000"/>
						<texcoord u="0.876900" v="-2.794700"/>
					</vertex>
					<vertex>
						<position x="-2457.372070" y="-23.941000" z="-2799.020996"/>
						<normal x="0.000000" y="1.000000" z="0.000000"/>
						<texcoord u="1.025100" v="-2.920700"/>
					</vertex>
					<vertex>
						<position x="-2457.324951" y="-23.941000" z="-2799.093018"/>
						<normal x="0.000000" y="1.000000" z="0.000000"/>
						<texcoord u="1.031700" v="-2.907900"/>
					</vertex>
					<vertex>
						<position x="-2456.511963" y="-23.941000" z="-2798.361084"/>
						<normal x="-0.000000" y="1.000000" z="0.000000"/>
						<texcoord u="1.178900" v="-3.015500"/>
					</vertex>
					<vertex>
						<position x="-2438.354004" y="-24.469999" z="-2808.922119"/>
						<normal x="0.109164" y="0.983921" z="0.141363"/>
						<texcoord u="4.010400" v="-0.956500"/>
					</vertex>
					<vertex>
						<position x="-2438.762939" y="-24.361000" z="-2809.364990"/>
						<normal x="0.109164" y="0.983921" z="0.141363"/>
						<texcoord u="3.935100" v="-0.890000"/>
					</vertex>
					<vertex>
						<position x="-2438.806885" y="-24.361000" z="-2809.331055"/>
						<normal x="0.109164" y="0.983921" z="0.141363"/>
						<texcoord u="3.928300" v="-0.896400"/>
					</vertex>
					<vertex>
						<position x="-2438.762939" y="-24.361000" z="-2809.364990"/>
						<normal x="0.104068" y="0.983405" z="0.148607"/>
						<texcoord u="3.935100" v="-0.890000"/>
					</vertex>
					<vertex>
						<position x="-2439.084961" y="-24.250000" z="-2809.874023"/>
						<normal x="0.104068" y="0.983405" z="0.148607"/>
						<texcoord u="3.873100" v="-0.811000"/>
					</vertex>
					<vertex>
						<position x="-2439.292969" y="-24.243999" z="-2809.768066"/>
						<normal x="0.104068" y="0.983405" z="0.148607"/>
						<texcoord u="3.840400" v="-0.832200"/>
					</vertex>
					<vertex>
						<position x="-2438.806885" y="-24.361000" z="-2809.331055"/>
						<normal x="0.104068" y="0.983405" z="0.148607"/>
						<texcoord u="3.928300" v="-0.896400"/>
					</vertex>
					<vertex>
						<position x="-2439.084961" y="-24.250000" z="-2809.874023"/>
						<normal x="0.090395" y="0.981166" z="0.170708"/>
						<texcoord u="3.873100" v="-0.811000"/>
					</vertex>
					<vertex>
						<position x="-2439.308105" y="-24.132000" z="-2810.434082"/>
						<normal x="0.090395" y="0.981166" z="0.170708"/>
						<texcoord u="3.826500" v="-0.722000"/>
					</vertex>
					<vertex>
						<position x="-2439.853027" y="-24.110001" z="-2810.271973"/>
						<normal x="0.090395" y="0.981166" z="0.170708"/>
						<texcoord u="3.739100" v="-0.758100"/>
					</vertex>
					<vertex>
						<position x="-2439.292969" y="-24.243999" z="-2809.768066"/>
						<normal x="0.090395" y="0.981166" z="0.170708"/>
						<texcoord u="3.840400" v="-0.832200"/>
					</vertex>
					<vertex>
						<position x="-2439.308105" y="-24.132000" z="-2810.434082"/>
						<normal x="0.076424" y="0.977858" z="0.194818"/>
						<texcoord u="3.826500" v="-0.722000"/>
					</vertex>
					<vertex>
						<position x="-2439.427002" y="-24.004999" z="-2811.024902"/>
						<normal x="0.076424" y="0.977858" z="0.194818"/>
						<texcoord u="3.796800" v="-0.626100"/>
					</vertex>
					<vertex>
						<position x="-2440.553955" y="-23.941000" z="-2810.904053"/>
						<normal x="0.076424" y="0.977858" z="0.194818"/>
						<texcoord u="3.611900" v="-0.665200"/>
					</vertex>
					<vertex>
						<position x="-2439.853027" y="-24.110001" z="-2810.271973"/>
						<normal x="0.076424" y="0.977858" z="0.194818"/>
						<texcoord u="3.739100" v="-0.758100"/>
					</vertex>
					<vertex>
						<position x="-2439.427002" y="-24.004999" z="-2811.024902"/>
						<normal x="0.041670" y="0.996149" z="0.077139"/>
						<texcoord u="3.796800" v="-0.626100"/>
					</vertex>
					<vertex>
						<position x="-2439.436035" y="-23.958000" z="-2811.626953"/>
						<normal x="0.041670" y="0.996149" z="0.077139"/>
						<texcoord u="3.785100" v="-0.526300"/>
					</vertex>
					<vertex>
						<position x="-2440.001953" y="-23.931000" z="-2811.669922"/>
						<normal x="0.041670" y="0.996149" z="0.077139"/>
						<texcoord u="3.690600" v="-0.528700"/>
					</vertex>
					<vertex>
						<position x="-2440.553955" y="-23.941000" z="-2810.904053"/>
						<normal x="0.041670" y="0.996149" z="0.077139"/>
						<texcoord u="3.611900" v="-0.665200"/>
					</vertex>
					<vertex>
						<position x="-2439.436035" y="-23.958000" z="-2811.626953"/>
						<normal x="0.022268" y="0.998542" z="0.049179"/>
						<texcoord u="3.785100" v="-0.526300"/>
					</vertex>
					<vertex>
						<position x="-2439.334961" y="-23.931000" z="-2812.220947"/>
						<normal x="0.022268" y="0.998542" z="0.049179"/>
						<texcoord u="3.791700" v="-0.426100"/>
					</vertex>
					<vertex>
						<position x="-2439.561035" y="-23.923000" z="-2812.281006"/>
						<normal x="0.022268" y="0.998542" z="0.049179"/>
						<texcoord u="3.753300" v="-0.420000"/>
					</vertex>
					<vertex>
						<position x="-2440.001953" y="-23.931000" z="-2811.669922"/>
						<normal x="0.022268" y="0.998542" z="0.049179"/>
						<texcoord u="3.690600" v="-0.528700"/>
					</vertex>
					<vertex>
						<position x="-2439.334961" y="-23.931000" z="-2812.220947"/>
						<normal x="0.006113" y="0.999569" z="0.028717"/>
						<texcoord u="3.791700" v="-0.426100"/>
					</vertex>
					<vertex>
						<position x="-2439.127930" y="-23.916000" z="-2812.787109"/>
						<normal x="0.006113" y="0.999569" z="0.028717"/>
						<texcoord u="3.816400" v="-0.328800"/>
					</vertex>
					<vertex>
						<position x="-2439.178955" y="-23.915001" z="-2812.811035"/>
						<normal x="0.006113" y="0.999569" z="0.028717"/>
						<texcoord u="3.807700" v="-0.325600"/>
					</vertex>
					<vertex>
						<position x="-2439.561035" y="-23.923000" z="-2812.281006"/>
						<normal x="0.006113" y="0.999569" z="0.028717"/>
						<texcoord u="3.753300" v="-0.420000"/>
					</vertex>
					<vertex>
						<position x="-2439.127930" y="-23.916000" z="-2812.787109"/>
						<normal x="0.010386" y="0.999754" z="0.019613"/>
						<texcoord u="3.816400" v="-0.328800"/>
					</vertex>
					<vertex>
						<position x="-2438.822021" y="-23.909000" z="-2813.305908"/>
						<normal x="0.010386" y="0.999754" z="0.019613"/>
						<texcoord u="3.858500" v="-0.237500"/>
					</vertex>
					<vertex>
						<position x="-2439.178955" y="-23.915001" z="-2812.811035"/>
						<normal x="0.010386" y="0.999754" z="0.019613"/>
						<texcoord u="3.807700" v="-0.325600"/>
					</vertex>
					<vertex>
						<position x="-2457.032959" y="-23.941000" z="-2822.246094"/>
						<normal x="0.067504" y="0.996527" z="0.048753"/>
						<texcoord u="0.687300" v="0.935700"/>
					</vertex>
					<vertex>
						<position x="-2457.575928" y="-23.934999" z="-2821.616943"/>
						<normal x="0.067504" y="0.996527" z="0.048753"/>
						<texcoord u="0.608000" v="0.822300"/>
					</vertex>
					<vertex>
						<position x="-2457.524902" y="-23.941000" z="-2821.564941"/>
						<normal x="0.067504" y="0.996527" z="0.048753"/>
						<texcoord u="0.617400" v="0.814500"/>
					</vertex>
					<vertex>
						<position x="-2457.575928" y="-23.934999" z="-2821.616943"/>
						<normal x="0.033894" y="0.999024" z="0.028317"/>
						<texcoord u="0.608000" v="0.822300"/>
					</vertex>
					<vertex>
						<position x="-2458.219971" y="-23.927999" z="-2821.093018"/>
						<normal x="0.033894" y="0.999024" z="0.028317"/>
						<texcoord u="0.510200" v="0.724400"/>
					</vertex>
					<vertex>
						<position x="-2458.048096" y="-23.941000" z="-2820.840088"/>
						<normal x="0.033894" y="0.999024" z="0.028317"/>
						<texcoord u="0.542900" v="0.685400"/>
					</vertex>
					<vertex>
						<position x="-2457.524902" y="-23.941000" z="-2821.564941"/>
						<normal x="0.033894" y="0.999024" z="0.028317"/>
						<texcoord u="0.617400" v="0.814500"/>
					</vertex>
					<vertex>
						<position x="-2458.219971" y="-23.927999" z="-2821.093018"/>
						<normal x="0.019231" y="0.999622" z="0.019623"/>
						<texcoord u="0.510200" v="0.724400"/>
					</vertex>
					<vertex>
						<position x="-2458.945068" y="-23.922001" z="-2820.687988"/>
						<normal x="0.019231" y="0.999622" z="0.019623"/>
						<texcoord u="0.396900" v="0.645100"/>
					</vertex>
					<vertex>
						<position x="-2458.643066" y="-23.941000" z="-2820.016113"/>
						<normal x="0.019231" y="0.999622" z="0.019623"/>
						<texcoord u="0.458300" v="0.538700"/>
					</vertex>
					<vertex>
						<position x="-2458.048096" y="-23.941000" z="-2820.840088"/>
						<normal x="0.019231" y="0.999622" z="0.019623"/>
						<texcoord u="0.542900" v="0.685400"/>
					</vertex>
					<vertex>
						<position x="-2458.945068" y="-23.922001" z="-2820.687988"/>
						<normal x="0.111406" y="0.993710" z="-0.011377"/>
						<texcoord u="0.396900" v="0.645100"/>
					</vertex>
					<vertex>
						<position x="-2459.729004" y="-23.830999" z="-2820.416016"/>
						<normal x="0.111406" y="0.993710" z="-0.011377"/>
						<texcoord u="0.271500" v="0.586500"/>
					</vertex>
					<vertex>
						<position x="-2459.654053" y="-23.836000" z="-2820.118896"/>
						<normal x="0.111406" y="0.993710" z="-0.011377"/>
						<texcoord u="0.288900" v="0.538700"/>
					</vertex>
					<vertex>
						<position x="-2458.643066" y="-23.941000" z="-2820.016113"/>
						<normal x="0.111406" y="0.993710" z="-0.011377"/>
						<texcoord u="0.458300" v="0.538700"/>
					</vertex>
					<vertex>
						<position x="-2459.729004" y="-23.830999" z="-2820.416016"/>
						<normal x="0.107789" y="0.994155" z="0.006041"/>
						<texcoord u="0.271500" v="0.586500"/>
					</vertex>
					<vertex>
						<position x="-2460.548096" y="-23.743000" z="-2820.282959"/>
						<normal x="0.107789" y="0.994155" z="0.006041"/>
						<texcoord u="0.137900" v="0.550700"/>
					</vertex>
					<vertex>
						<position x="-2460.542969" y="-23.743999" z="-2820.209961"/>
						<normal x="0.107789" y="0.994155" z="0.006041"/>
						<texcoord u="0.140000" v="0.538700"/>
					</vertex>
					<vertex>
						<position x="-2459.654053" y="-23.836000" z="-2820.118896"/>
						<normal x="0.107789" y="0.994155" z="0.006041"/>
						<texcoord u="0.288900" v="0.538700"/>
					</vertex>
					<vertex>
						<position x="-2460.548096" y="-23.743000" z="-2820.282959"/>
						<normal x="0.102990" y="0.994662" z="0.006385"/>
						<texcoord u="0.137900" v="0.550700"/>
					</vertex>
					<vertex>
						<position x="-2461.377930" y="-23.657000" z="-2820.294922"/>
						<normal x="0.102990" y="0.994662" z="0.006385"/>
						<texcoord u="0.000000" v="0.538600"/>
					</vertex>
					<vertex>
						<position x="-2460.542969" y="-23.743999" z="-2820.209961"/>
						<normal x="0.102990" y="0.994662" z="0.006385"/>
						<texcoord u="0.140000" v="0.538700"/>
					</vertex>
					<vertex>
						<position x="271.500000" y="-99.991997" z="579.127014"/>
						<normal x="-0.001813" y="0.999983" z="-0.005614"/>
						<texcoord u="0.000000" v="0.983200"/>
					</vertex>
					<vertex>
						<position x="270.980988" y="-100.000000" z="577.869019"/>
						<normal x="-0.001813" y="0.999983" z="-0.005614"/>
						<texcoord u="0.226800" v="0.983200"/>
					</vertex>
					<vertex>
						<position x="270.885010" y="-100.000000" z="577.900024"/>
						<normal x="-0.001813" y="0.999983" z="-0.005614"/>
						<texcoord u="0.228000" v="1.000000"/>
					</vertex>
					<vertex>
						<position x="270.980988" y="-100.000000" z="577.869019"/>
						<normal x="-0.000453" y="0.999999" z="-0.001401"/>
						<texcoord u="0.226800" v="0.983200"/>
					</vertex>
					<vertex>
						<position x="270.653015" y="-100.001999" z="576.547974"/>
						<normal x="-0.000453" y="0.999999" z="-0.001401"/>
						<texcoord u="0.451200" v="0.949900"/>
					</vertex>
					<vertex>
						<position x="270.885010" y="-100.000000" z="577.900024"/>
						<normal x="-0.000453" y="0.999999" z="-0.001401"/>
						<texcoord u="0.228000" v="1.000000"/>
					</vertex>
					<vertex>
						<position x="838.473999" y="-9.829000" z="1103.282959"/>
						<normal x="-0.007343" y="0.999793" z="-0.018958"/>
						<texcoord u="0.000000" v="0.986700"/>
					</vertex>
					<vertex>
						<position x="838.981018" y="-9.804000" z="1104.405029"/>
						<normal x="-0.007343" y="0.999793" z="-0.018958"/>
						<texcoord u="0.205200" v="0.986700"/>
					</vertex>
					<vertex>
						<position x="839.056030" y="-9.804000" z="1104.375977"/>
						<normal x="-0.007343" y="0.999793" z="-0.018958"/>
						<texcoord u="0.206100" v="1.000000"/>
					</vertex>
					<vertex>
						<position x="838.981018" y="-9.804000" z="1104.405029"/>
						<normal x="0.005884" y="0.999867" z="0.015191"/>
						<texcoord u="0.205200" v="0.986700"/>
					</vertex>
					<vertex>
						<position x="839.341003" y="-9.824000" z="1105.582031"/>
						<normal x="0.005884" y="0.999867" z="0.015191"/>
						<texcoord u="0.408700" v="0.960300"/>
					</vertex>
					<vertex>
						<position x="839.056030" y="-9.804000" z="1104.375977"/>
						<normal x="0.005884" y="0.999867" z="0.015191"/>
						<texcoord u="0.206100" v="1.000000"/>
					</vertex>
					<vertex>
						<position x="811.151978" y="-10.989000" z="1055.152954"/>
						<normal x="0.000000" y="1.000000" z="0.000000"/>
						<texcoord u="0.605200" v="-2.769900"/>
					</vertex>
					<vertex>
						<position x="812.143982" y="-10.989000" z="1055.673950"/>
						<normal x="0.000000" y="1.000000" z="0.000000"/>
						<texcoord u="0.791200" v="-2.785800"/>
					</vertex>
					<vertex>
						<position x="812.195984" y="-10.989000" z="1055.592041"/>
						<normal x="0.000000" y="1.000000" z="0.000000"/>
						<texcoord u="0.793900" v="-2.769900"/>
					</vertex>
					<vertex>
						<position x="813.031982" y="-10.989000" z="1056.355957"/>
						<normal x="0.000000" y="1.000000" z="0.000000"/>
						<texcoord u="0.971800" v="-2.833000"/>
					</vertex>
					<vertex>
						<position x="813.302979" y="-10.989000" z="1056.058960"/>
						<normal x="0.000000" y="1.000000" z="0.000000"/>
						<texcoord u="0.994200" v="-2.769900"/>
					</vertex>
					<vertex>
						<position x="813.791992" y="-10.989000" z="1057.177979"/>
						<normal x="0.000000" y="1.000000" z="0.000000"/>
						<texcoord u="1.141700" v="-2.910300"/>
					</vertex>
					<vertex>
						<position x="813.869019" y="-10.989000" z="1057.119019"/>
						<normal x="0.000000" y="1.000000" z="0.000000"/>
						<texcoord u="1.149600" v="-2.896200"/>
					</vertex>
					<vertex>
						<position x="814.401001" y="-10.989000" z="1058.118042"/>
						<normal x="-0.000000" y="1.000000" z="0.000000"/>
						<texcoord u="1.296000" v="-3.015300"/>
					</vertex>
					<vertex>
						<position x="834.143982" y="-10.932000" z="1052.640015"/>
						<normal x="-0.006137" y="0.999811" z="-0.018434"/>
						<texcoord u="3.974600" v="-0.897100"/>
					</vertex>
					<vertex>
						<position x="833.898010" y="-10.944000" z="1052.071045"/>
						<normal x="-0.006137" y="0.999811" z="-0.018434"/>
						<texcoord u="3.899900" v="-0.825800"/>
					</vertex>
					<vertex>
						<position x="833.849976" y="-10.944000" z="1052.087036"/>
						<normal x="-0.006137" y="0.999811" z="-0.018434"/>
						<texcoord u="3.893700" v="-0.831300"/>
					</vertex>
					<vertex>
						<position x="833.898010" y="-10.944000" z="1052.071045"/>
						<normal x="-0.008305" y="0.999775" z="-0.019508"/>
						<texcoord u="3.899900" v="-0.825800"/>
					</vertex>
					<vertex>
						<position x="833.744995" y="-10.957000" z="1051.469971"/>
						<normal x="-0.008305" y="0.999775" z="-0.019508"/>
						<texcoord u="3.837600" v="-0.743400"/>
					</vertex>
					<vertex>
						<position x="833.539978" y="-10.958000" z="1051.505981"/>
						<normal x="-0.008305" y="0.999775" z="-0.019508"/>
						<texcoord u="3.808500" v="-0.762000"/>
					</vertex>
					<vertex>
						<position x="833.849976" y="-10.944000" z="1052.087036"/>
						<normal x="-0.008305" y="0.999775" z="-0.019508"/>
						<texcoord u="3.893700" v="-0.831300"/>
					</vertex>
					<vertex>
						<position x="833.744995" y="-10.957000" z="1051.469971"/>
						<normal x="-0.006263" y="0.999802" z="-0.018879"/>
						<texcoord u="3.837600" v="-0.743400"/>
					</vertex>
					<vertex>
						<position x="833.689026" y="-10.969000" z="1050.853027"/>
						<normal x="-0.006263" y="0.999802" z="-0.018879"/>
						<texcoord u="3.789200" v="-0.652200"/>
					</vertex>
					<vertex>
						<position x="833.195007" y="-10.972000" z="1050.858032"/>
						<normal x="-0.006263" y="0.999802" z="-0.018879"/>
						<texcoord u="3.713500" v="-0.684800"/>
					</vertex>
					<vertex>
						<position x="833.539978" y="-10.958000" z="1051.505981"/>
						<normal x="-0.006263" y="0.999802" z="-0.018879"/>
						<texcoord u="3.808500" v="-0.762000"/>
					</vertex>
					<vertex>
						<position x="833.689026" y="-10.969000" z="1050.853027"/>
						<normal x="-0.004171" y="0.999764" z="-0.021327"/>
						<texcoord u="3.789200" v="-0.652200"/>
					</vertex>
					<vertex>
						<position x="833.732971" y="-10.982000" z="1050.234985"/>
						<normal x="-0.004171" y="0.999764" z="-0.021327"/>
						<texcoord u="3.755900" v="-0.554400"/>
					</vertex>
					<vertex>
						<position x="832.786011" y="-10.989000" z="1050.092041"/>
						<normal x="-0.004171" y="0.999764" z="-0.021327"/>
						<texcoord u="3.601200" v="-0.593500"/>
					</vertex>
					<vertex>
						<position x="833.195007" y="-10.972000" z="1050.858032"/>
						<normal x="-0.004171" y="0.999764" z="-0.021327"/>
						<texcoord u="3.713500" v="-0.684800"/>
					</vertex>
					<vertex>
						<position x="833.732971" y="-10.982000" z="1050.234985"/>
						<normal x="-0.006417" y="0.999979" z="0.000148"/>
						<texcoord u="3.755900" v="-0.554400"/>
					</vertex>
					<vertex>
						<position x="833.875000" y="-10.981000" z="1049.631958"/>
						<normal x="-0.006417" y="0.999979" z="0.000148"/>
						<texcoord u="3.738700" v="-0.452500"/>
					</vertex>
					<vertex>
						<position x="833.403992" y="-10.984000" z="1049.480957"/>
						<normal x="-0.006417" y="0.999979" z="0.000148"/>
						<texcoord u="3.656600" v="-0.459800"/>
					</vertex>
					<vertex>
						<position x="832.786011" y="-10.989000" z="1050.092041"/>
						<normal x="-0.006417" y="0.999979" z="0.000148"/>
						<texcoord u="3.601200" v="-0.593500"/>
					</vertex>
					<vertex>
						<position x="833.875000" y="-10.981000" z="1049.631958"/>
						<normal x="-0.005934" y="0.999982" z="0.001046"/>
						<texcoord u="3.738700" v="-0.452500"/>
					</vertex>
					<vertex>
						<position x="834.111023" y="-10.979000" z="1049.058960"/>
						<normal x="-0.005934" y="0.999982" z="0.001046"/>
						<texcoord u="3.737900" v="-0.349200"/>
					</vertex>
					<vertex>
						<position x="833.926025" y="-10.980000" z="1048.964966"/>
						<normal x="-0.005934" y="0.999982" z="0.001046"/>
						<texcoord u="3.703400" v="-0.346800"/>
					</vertex>
					<vertex>
						<position x="833.403992" y="-10.984000" z="1049.480957"/>
						<normal x="-0.005934" y="0.999982" z="0.001046"/>
						<texcoord u="3.656600" v="-0.459800"/>
					</vertex>
					<vertex>
						<position x="834.111023" y="-10.979000" z="1049.058960"/>
						<normal x="-0.002871" y="0.999988" z="0.003921"/>
						<texcoord u="3.737900" v="-0.349200"/>
					</vertex>
					<vertex>
						<position x="834.434998" y="-10.976000" z="1048.531006"/>
						<normal x="-0.002871" y="0.999988" z="0.003921"/>
						<texcoord u="3.753600" v="-0.247200"/>
					</vertex>
					<vertex>
						<position x="834.393982" y="-10.976000" z="1048.500977"/>
						<normal x="-0.002871" y="0.999988" z="0.003921"/>
						<texcoord u="3.745400" v="-0.245200"/>
					</vertex>
					<vertex>
						<position x="833.926025" y="-10.980000" z="1048.964966"/>
						<normal x="-0.002871" y="0.999988" z="0.003921"/>
						<texcoord u="3.703400" v="-0.346800"/>
					</vertex>
					<vertex>
						<position x="834.434998" y="-10.976000" z="1048.531006"/>
						<normal x="-0.002866" y="0.999988" z="0.003914"/>
						<texcoord u="3.753600" v="-0.247200"/>
					</vertex>
					<vertex>
						<position x="834.840027" y="-10.973000" z="1048.061035"/>
						<normal x="-0.002866" y="0.999988" z="0.003914"/>
						<texcoord u="3.785300" v="-0.148900"/>
					</vertex>
					<vertex>
						<position x="834.393982" y="-10.976000" z="1048.500977"/>
						<normal x="-0.002866" y="0.999988" z="0.003914"/>
						<texcoord u="3.745400" v="-0.245200"/>
					</vertex>
					<vertex>
						<position x="820.192993" y="-10.973000" z="1034.416992"/>
						<normal x="-0.013620" y="0.999893" z="-0.005340"/>
						<texcoord u="0.653300" v="1.000000"/>
					</vertex>
					<vertex>
						<position x="819.546997" y="-10.979000" z="1034.941040"/>
						<normal x="-0.013620" y="0.999893" z="-0.005340"/>
						<texcoord u="0.587900" v="0.877700"/>
					</vertex>
					<vertex>
						<position x="819.593018" y="-10.978000" z="1035.010986"/>
						<normal x="-0.013620" y="0.999893" z="-0.005340"/>
						<texcoord u="0.599400" v="0.870000"/>
					</vertex>
					<vertex>
						<position x="819.546997" y="-10.979000" z="1034.941040"/>
						<normal x="-0.019191" y="0.999759" z="-0.010639"/>
						<texcoord u="0.587900" v="0.877700"/>
					</vertex>
					<vertex>
						<position x="818.810974" y="-10.989000" z="1035.328979"/>
						<normal x="-0.019191" y="0.999759" z="-0.010639"/>
						<texcoord u="0.500000" v="0.770600"/>
					</vertex>
					<vertex>
						<position x="818.943970" y="-10.983000" z="1035.652954"/>
						<normal x="-0.019191" y="0.999759" z="-0.010639"/>
						<texcoord u="0.541200" v="0.729400"/>
					</vertex>
					<vertex>
						<position x="819.593018" y="-10.978000" z="1035.010986"/>
						<normal x="-0.019191" y="0.999759" z="-0.010639"/>
						<texcoord u="0.599400" v="0.870000"/>
					</vertex>
					<vertex>
						<position x="818.810974" y="-10.989000" z="1035.328979"/>
						<normal x="-0.027337" y="0.999498" z="-0.016017"/>
						<texcoord u="0.500000" v="0.770600"/>
					</vertex>
					<vertex>
						<position x="818.013977" y="-11.007000" z="1035.566040"/>
						<normal x="-0.027337" y="0.999498" z="-0.016017"/>
						<texcoord u="0.392900" v="0.682600"/>
					</vertex>
					<vertex>
						<position x="818.177002" y="-10.989000" z="1036.411011"/>
						<normal x="-0.027337" y="0.999498" z="-0.016017"/>
						<texcoord u="0.472500" v="0.563400"/>
					</vertex>
					<vertex>
						<position x="818.943970" y="-10.983000" z="1035.652954"/>
						<normal x="-0.027337" y="0.999498" z="-0.016017"/>
						<texcoord u="0.541200" v="0.729400"/>
					</vertex>
					<vertex>
						<position x="818.013977" y="-11.007000" z="1035.566040"/>
						<normal x="-0.088911" y="0.995969" z="-0.011875"/>
						<texcoord u="0.392900" v="0.682600"/>
					</vertex>
					<vertex>
						<position x="817.185974" y="-11.080000" z="1035.642944"/>
						<normal x="-0.088911" y="0.995969" z="-0.011875"/>
						<texcoord u="0.270600" v="0.617300"/>
					</vertex>
					<vertex>
						<position x="817.184021" y="-11.076000" z="1035.993042"/>
						<normal x="-0.088911" y="0.995969" z="-0.011875"/>
						<texcoord u="0.292900" v="0.563500"/>
					</vertex>
					<vertex>
						<position x="818.177002" y="-10.989000" z="1036.411011"/>
						<normal x="-0.088911" y="0.995969" z="-0.011875"/>
						<texcoord u="0.472500" v="0.563400"/>
					</vertex>
					<vertex>
						<position x="817.185974" y="-11.080000" z="1035.642944"/>
						<normal x="-0.081370" y="0.996537" z="-0.017121"/>
						<texcoord u="0.270600" v="0.617300"/>
					</vertex>
					<vertex>
						<position x="816.359009" y="-11.149000" z="1035.557007"/>
						<normal x="-0.081370" y="0.996537" z="-0.017121"/>
						<texcoord u="0.138000" v="0.577000"/>
					</vertex>
					<vertex>
						<position x="816.341980" y="-11.149000" z="1035.637939"/>
						<normal x="-0.081370" y="0.996537" z="-0.017121"/>
						<texcoord u="0.140700" v="0.563400"/>
					</vertex>
					<vertex>
						<position x="817.184021" y="-11.076000" z="1035.993042"/>
						<normal x="-0.081370" y="0.996537" z="-0.017121"/>
						<texcoord u="0.292900" v="0.563500"/>
					</vertex>
					<vertex>
						<position x="816.359009" y="-11.149000" z="1035.557007"/>
						<normal x="-0.078869" y="0.996747" z="-0.016595"/>
						<texcoord u="0.138000" v="0.577000"/>
					</vertex>
					<vertex>
						<position x="815.564026" y="-11.216000" z="1035.311035"/>
						<normal x="-0.078869" y="0.996747" z="-0.016595"/>
						<texcoord u="0.000000" v="0.563400"/>
					</vertex>
					<vertex>
						<position x="816.341980" y="-11.149000" z="1035.637939"/>
						<normal x="-0.078869" y="0.996747" z="-0.016595"/>
						<texcoord u="0.140700" v="0.563400"/>
					</vertex>
					<vertex>
						<position x="-2544.827881" y="-14.553000" z="-2793.981934"/>
						<normal x="0.008020" y="0.999917" z="-0.010070"/>
						<texcoord u="0.000000" v="0.976300"/>
					</vertex>
					<vertex>
						<position x="-2544.257080" y="-14.566000" z="-2794.818115"/>
						<normal x="0.008020" y="0.999917" z="-0.010070"/>
						<texcoord u="0.168700" v="0.976400"/>
					</vertex>
					<vertex>
						<position x="-2544.311035" y="-14.566000" z="-2794.861084"/>
						<normal x="0.008020" y="0.999917" z="-0.010070"/>
						<texcoord u="0.169500" v="0.987900"/>
					</vertex>
					<vertex>
						<position x="-2544.257080" y="-14.566000" z="-2794.818115"/>
						<normal x="0.019160" y="0.999809" z="-0.003953"/>
						<texcoord u="0.168700" v="0.976400"/>
					</vertex>
					<vertex>
						<position x="-2543.576904" y="-14.582000" z="-2795.568115"/>
						<normal x="0.019160" y="0.999809" z="-0.003953"/>
						<texcoord u="0.335900" v="0.953300"/>
					</vertex>
					<vertex>
						<position x="-2543.775879" y="-14.579000" z="-2795.773926"/>
						<normal x="0.019160" y="0.999809" z="-0.003953"/>
						<texcoord u="0.345600" v="1.000000"/>
					</vertex>
					<vertex>
						<position x="-2544.311035" y="-14.566000" z="-2794.861084"/>
						<normal x="0.019160" y="0.999809" z="-0.003953"/>
						<texcoord u="0.169500" v="0.987900"/>
					</vertex>
					<vertex>
						<position x="-2543.576904" y="-14.582000" z="-2795.568115"/>
						<normal x="0.063896" y="0.997517" z="-0.029625"/>
						<texcoord u="0.335900" v="0.953300"/>
					</vertex>
					<vertex>
						<position x="-2542.801025" y="-14.651000" z="-2796.218018"/>
						<normal x="0.063896" y="0.997517" z="-0.029625"/>
						<texcoord u="0.498300" v="0.907600"/>
					</vertex>
					<vertex>
						<position x="-2542.843018" y="-14.650000" z="-2796.274902"/>
						<normal x="0.063896" y="0.997517" z="-0.029625"/>
						<texcoord u="0.502200" v="0.918600"/>
					</vertex>
					<vertex>
						<position x="-2543.775879" y="-14.579000" z="-2795.773926"/>
						<normal x="0.063896" y="0.997517" z="-0.029625"/>
						<texcoord u="0.345600" v="1.000000"/>
					</vertex>
					<vertex>
						<position x="-2542.801025" y="-14.651000" z="-2796.218018"/>
						<normal x="0.060812" y="0.997775" z="-0.027344"/>
						<texcoord u="0.498300" v="0.907600"/>
					</vertex>
					<vertex>
						<position x="-2541.944092" y="-14.718000" z="-2796.757080"/>
						<normal x="0.060812" y="0.997775" z="-0.027344"/>
						<texcoord u="0.653000" v="0.840300"/>
					</vertex>
					<vertex>
						<position x="-2542.843018" y="-14.650000" z="-2796.274902"/>
						<normal x="0.060812" y="0.997775" z="-0.027344"/>
						<texcoord u="0.502200" v="0.918600"/>
					</vertex>
					<vertex>
						<position x="-23.131001" y="-100.000000" z="7.455000"/>
						<normal x="0.000000" y="1.000000" z="0.000000"/>
						<texcoord u="0.000000" v="0.000000"/>
					</vertex>
					<vertex>
						<position x="-37.321999" y="-100.000000" z="-16.981001"/>
						<normal x="0.000000" y="1.000000" z="0.000000"/>
						<texcoord u="4.709500" v="0.000000"/>
					</vertex>
					<vertex>
						<position x="-40.537998" y="-100.000000" z="-10.571000"/>
						<normal x="0.000000" y="1.000000" z="0.000000"/>
						<texcoord u="4.054800" v="1.000000"/>
					</vertex>
					<vertex>
						<position x="-30.374001" y="-100.000000" z="6.930000"/>
						<normal x="0.000000" y="1.000000" z="0.000000"/>
						<texcoord u="0.681800" v="1.000000"/>
					</vertex>
					<vertex>
						<position x="-20.409000" y="-100.000000" z="-27.681999"/>
						<normal x="0.000000" y="1.000000" z="0.000000"/>
						<texcoord u="0.000000" v="-0.001200"/>
					</vertex>
					<vertex>
						<position x="-5.613000" y="-100.000000" z="-2.183000"/>
						<normal x="0.000000" y="1.000000" z="0.000000"/>
						<texcoord u="4.913500" v="-0.001200"/>
					</vertex>
					<vertex>
						<position x="-2.572000" y="-100.000000" z="-8.912000"/>
						<normal x="0.000000" y="1.000000" z="0.000000"/>
						<texcoord u="4.197700" v="1.000000"/>
					</vertex>
					<vertex>
						<position x="-13.077000" y="-100.000000" z="-27.016001"/>
						<normal x="0.000000" y="1.000000" z="0.000000"/>
						<texcoord u="0.709300" v="1.000000"/>
					</vertex>
					<vertex>
						<position x="832.786011" y="-10.989000" z="1050.092041"/>
						<normal x="0.000000" y="1.000000" z="0.000000"/>
						<texcoord u="3.601200" v="-0.593500"/>
					</vertex>
					<vertex>
						<position x="818.177002" y="-10.989000" z="1036.411011"/>
						<normal x="0.000000" y="1.000000" z="0.000000"/>
						<texcoord u="0.472500" v="0.563400"/>
					</vertex>
					<vertex>
						<position x="810.418030" y="-10.989000" z="1054.843994"/>
						<normal x="0.000000" y="1.000000" z="0.000000"/>
						<texcoord u="0.472500" v="-2.769900"/>
					</vertex>
					<vertex>
						<position x="815.137024" y="-10.989000" z="1059.498047"/>
						<normal x="0.000000" y="1.000000" z="0.000000"/>
						<texcoord u="1.498300" v="-3.179700"/>
					</vertex>
					<vertex>
						<position x="-2440.553955" y="-23.941000" z="-2810.904053"/>
						<normal x="0.000000" y="1.000000" z="0.000000"/>
						<texcoord u="3.611900" v="-0.665200"/>
					</vertex>
					<vertex>
						<position x="-2456.772949" y="-23.941000" z="-2822.606934"/>
						<normal x="0.000000" y="1.000000" z="0.000000"/>
						<texcoord u="0.724300" v="1.000000"/>
					</vertex>
					<vertex>
						<position x="-2458.643066" y="-23.941000" z="-2820.016113"/>
						<normal x="0.000000" y="1.000000" z="0.000000"/>
						<texcoord u="0.458300" v="0.538700"/>
					</vertex>
					<vertex>
						<position x="-2460.677979" y="-23.941000" z="-2800.118896"/>
						<normal x="0.000000" y="1.000000" z="0.000000"/>
						<texcoord u="0.458300" v="-2.794700"/>
					</vertex>
					<vertex>
						<position x="-2453.939941" y="-23.941000" z="-2796.043945"/>
						<normal x="0.000000" y="1.000000" z="0.000000"/>
						<texcoord u="1.644700" v="-3.356000"/>
					</vertex>
				</vertexbuffer>
			</geometry>
		</submesh>
	</submeshes>
</mesh>
