<mesh>
	<submeshes>
		<submesh material="BuildGeneric_1.002" usesharedvertices="false">
			<faces count="68">
				<face v1="0" v2="1" v3="3"/>
				<face v1="1" v2="2" v3="3"/>
				<face v1="4" v2="5" v3="7"/>
				<face v1="5" v2="6" v3="7"/>
				<face v1="8" v2="9" v3="11"/>
				<face v1="9" v2="10" v3="11"/>
				<face v1="12" v2="13" v3="15"/>
				<face v1="13" v2="14" v3="15"/>
				<face v1="16" v2="17" v3="19"/>
				<face v1="17" v2="18" v3="19"/>
				<face v1="20" v2="21" v3="23"/>
				<face v1="21" v2="22" v3="23"/>
				<face v1="3" v2="2" v3="25"/>
				<face v1="2" v2="24" v3="25"/>
				<face v1="7" v2="6" v3="27"/>
				<face v1="6" v2="26" v3="27"/>
				<face v1="11" v2="10" v3="29"/>
				<face v1="10" v2="28" v3="29"/>
				<face v1="15" v2="14" v3="31"/>
				<face v1="14" v2="30" v3="31"/>
				<face v1="19" v2="18" v3="33"/>
				<face v1="18" v2="32" v3="33"/>
				<face v1="23" v2="22" v3="35"/>
				<face v1="22" v2="34" v3="35"/>
				<face v1="36" v2="37" v3="39"/>
				<face v1="37" v2="38" v3="39"/>
				<face v1="40" v2="41" v3="43"/>
				<face v1="41" v2="42" v3="43"/>
				<face v1="44" v2="45" v3="47"/>
				<face v1="45" v2="46" v3="47"/>
				<face v1="48" v2="49" v3="51"/>
				<face v1="49" v2="50" v3="51"/>
				<face v1="52" v2="53" v3="55"/>
				<face v1="53" v2="54" v3="55"/>
				<face v1="39" v2="38" v3="57"/>
				<face v1="38" v2="56" v3="57"/>
				<face v1="43" v2="42" v3="59"/>
				<face v1="42" v2="58" v3="59"/>
				<face v1="47" v2="46" v3="61"/>
				<face v1="46" v2="60" v3="61"/>
				<face v1="51" v2="50" v3="63"/>
				<face v1="50" v2="62" v3="63"/>
				<face v1="55" v2="54" v3="65"/>
				<face v1="54" v2="64" v3="65"/>
				<face v1="66" v2="67" v3="69"/>
				<face v1="67" v2="68" v3="69"/>
				<face v1="70" v2="71" v3="73"/>
				<face v1="71" v2="72" v3="73"/>
				<face v1="74" v2="75" v3="77"/>
				<face v1="75" v2="76" v3="77"/>
				<face v1="78" v2="79" v3="81"/>
				<face v1="79" v2="80" v3="81"/>
				<face v1="82" v2="83" v3="85"/>
				<face v1="83" v2="84" v3="85"/>
				<face v1="86" v2="87" v3="89"/>
				<face v1="87" v2="88" v3="89"/>
				<face v1="69" v2="68" v3="91"/>
				<face v1="68" v2="90" v3="91"/>
				<face v1="73" v2="72" v3="93"/>
				<face v1="72" v2="92" v3="93"/>
				<face v1="94" v2="95" v3="97"/>
				<face v1="95" v2="96" v3="97"/>
				<face v1="98" v2="99" v3="100"/>
				<face v1="98" v2="100" v3="101"/>
				<face v1="85" v2="84" v3="103"/>
				<face v1="84" v2="102" v3="103"/>
				<face v1="89" v2="88" v3="105"/>
				<face v1="88" v2="104" v3="105"/>
			</faces>
			<geometry vertexcount="106">
				<vertexbuffer positions="true" normals="true" texture_coords="1">
					<vertex>
						<position x="355.851990" y="0.250000" z="-124.267998"/>
						<normal x="0.974389" y="0.000000" z="0.224869"/>
						<texcoord u="0.000000" v="1.000000"/>
					</vertex>
					<vertex>
						<position x="355.890991" y="0.250000" z="-124.436996"/>
						<normal x="0.974389" y="0.000000" z="0.224869"/>
						<texcoord u="0.166700" v="1.000000"/>
					</vertex>
					<vertex>
						<position x="355.890991" y="4.750000" z="-124.436996"/>
						<normal x="0.974389" y="0.000000" z="0.224869"/>
						<texcoord u="0.166700" v="0.833400"/>
					</vertex>
					<vertex>
						<position x="355.851990" y="4.750000" z="-124.267998"/>
						<normal x="0.974389" y="0.000000" z="0.224869"/>
						<texcoord u="0.000000" v="0.833400"/>
					</vertex>
					<vertex>
						<position x="355.890991" y="0.250000" z="-124.436996"/>
						<normal x="0.954684" y="0.000000" z="-0.297621"/>
						<texcoord u="0.000000" v="1.000000"/>
					</vertex>
					<vertex>
						<position x="354.403015" y="0.250000" z="-129.210007"/>
						<normal x="0.954684" y="0.000000" z="-0.297621"/>
						<texcoord u="0.333300" v="1.000000"/>
					</vertex>
					<vertex>
						<position x="354.403015" y="4.750000" z="-129.210007"/>
						<normal x="0.954684" y="0.000000" z="-0.297621"/>
						<texcoord u="0.333300" v="0.833400"/>
					</vertex>
					<vertex>
						<position x="355.890991" y="4.750000" z="-124.436996"/>
						<normal x="0.954684" y="0.000000" z="-0.297621"/>
						<texcoord u="0.000000" v="0.833400"/>
					</vertex>
					<vertex>
						<position x="332.084991" y="0.250000" z="-112.481003"/>
						<normal x="0.444301" y="0.000000" z="0.895878"/>
						<texcoord u="0.000000" v="1.000000"/>
					</vertex>
					<vertex>
						<position x="355.851990" y="0.250000" z="-124.267998"/>
						<normal x="0.444301" y="0.000000" z="0.895878"/>
						<texcoord u="1.333300" v="1.000000"/>
					</vertex>
					<vertex>
						<position x="355.851990" y="4.750000" z="-124.267998"/>
						<normal x="0.444301" y="0.000000" z="0.895878"/>
						<texcoord u="1.333300" v="0.833400"/>
					</vertex>
					<vertex>
						<position x="332.084991" y="4.750000" z="-112.481003"/>
						<normal x="0.444301" y="0.000000" z="0.895878"/>
						<texcoord u="0.000000" v="0.833400"/>
					</vertex>
					<vertex>
						<position x="354.403015" y="0.250000" z="-129.210007"/>
						<normal x="0.675787" y="0.000000" z="-0.737097"/>
						<texcoord u="0.000000" v="1.000000"/>
					</vertex>
					<vertex>
						<position x="336.753998" y="0.250000" z="-145.391006"/>
						<normal x="0.675787" y="0.000000" z="-0.737097"/>
						<texcoord u="1.333300" v="1.000000"/>
					</vertex>
					<vertex>
						<position x="336.753998" y="4.750000" z="-145.391006"/>
						<normal x="0.675787" y="0.000000" z="-0.737097"/>
						<texcoord u="1.333300" v="0.833400"/>
					</vertex>
					<vertex>
						<position x="354.403015" y="4.750000" z="-129.210007"/>
						<normal x="0.675787" y="0.000000" z="-0.737097"/>
						<texcoord u="0.000000" v="0.833400"/>
					</vertex>
					<vertex>
						<position x="336.753998" y="0.250000" z="-145.391006"/>
						<normal x="0.675764" y="0.000000" z="-0.737118"/>
						<texcoord u="0.000000" v="1.000000"/>
					</vertex>
					<vertex>
						<position x="319.105011" y="0.250000" z="-161.570999"/>
						<normal x="0.675764" y="0.000000" z="-0.737118"/>
						<texcoord u="1.333300" v="1.000000"/>
					</vertex>
					<vertex>
						<position x="319.105011" y="4.750000" z="-161.570999"/>
						<normal x="0.675764" y="0.000000" z="-0.737118"/>
						<texcoord u="1.333300" v="0.833400"/>
					</vertex>
					<vertex>
						<position x="336.753998" y="4.750000" z="-145.391006"/>
						<normal x="0.675764" y="0.000000" z="-0.737118"/>
						<texcoord u="0.000000" v="0.833400"/>
					</vertex>
					<vertex>
						<position x="319.105011" y="0.250000" z="-161.570999"/>
						<normal x="-0.444068" y="0.000000" z="-0.895993"/>
						<texcoord u="0.000000" v="1.000000"/>
					</vertex>
					<vertex>
						<position x="309.979004" y="0.250000" z="-157.048004"/>
						<normal x="-0.444068" y="0.000000" z="-0.895993"/>
						<texcoord u="0.666700" v="1.000000"/>
					</vertex>
					<vertex>
						<position x="309.979004" y="4.750000" z="-157.048004"/>
						<normal x="-0.444068" y="0.000000" z="-0.895993"/>
						<texcoord u="0.666700" v="0.833400"/>
					</vertex>
					<vertex>
						<position x="319.105011" y="4.750000" z="-161.570999"/>
						<normal x="-0.444068" y="0.000000" z="-0.895993"/>
						<texcoord u="0.000000" v="0.833400"/>
					</vertex>
					<vertex>
						<position x="355.890991" y="18.858999" z="-124.436996"/>
						<normal x="0.974389" y="0.000000" z="0.224869"/>
						<texcoord u="0.166700" v="0.000000"/>
					</vertex>
					<vertex>
						<position x="355.851990" y="18.858999" z="-124.267998"/>
						<normal x="0.974389" y="0.000000" z="0.224869"/>
						<texcoord u="0.000000" v="0.000000"/>
					</vertex>
					<vertex>
						<position x="354.403015" y="18.858999" z="-129.210007"/>
						<normal x="0.954684" y="0.000000" z="-0.297621"/>
						<texcoord u="0.333300" v="0.000000"/>
					</vertex>
					<vertex>
						<position x="355.890991" y="18.858999" z="-124.436996"/>
						<normal x="0.954684" y="0.000000" z="-0.297621"/>
						<texcoord u="0.000000" v="0.000000"/>
					</vertex>
					<vertex>
						<position x="355.851990" y="18.858999" z="-124.267998"/>
						<normal x="0.444301" y="0.000000" z="0.895877"/>
						<texcoord u="1.333300" v="0.000000"/>
					</vertex>
					<vertex>
						<position x="332.084991" y="18.858999" z="-112.481003"/>
						<normal x="0.444301" y="0.000000" z="0.895877"/>
						<texcoord u="0.000000" v="0.000000"/>
					</vertex>
					<vertex>
						<position x="336.753998" y="18.858999" z="-145.391006"/>
						<normal x="0.675787" y="0.000000" z="-0.737097"/>
						<texcoord u="1.333300" v="0.000000"/>
					</vertex>
					<vertex>
						<position x="354.403015" y="18.858999" z="-129.210007"/>
						<normal x="0.675787" y="0.000000" z="-0.737097"/>
						<texcoord u="0.000000" v="0.000000"/>
					</vertex>
					<vertex>
						<position x="319.105011" y="18.858999" z="-161.570999"/>
						<normal x="0.675764" y="0.000000" z="-0.737118"/>
						<texcoord u="1.333300" v="0.000000"/>
					</vertex>
					<vertex>
						<position x="336.753998" y="18.858999" z="-145.391006"/>
						<normal x="0.675764" y="0.000000" z="-0.737118"/>
						<texcoord u="0.000000" v="0.000000"/>
					</vertex>
					<vertex>
						<position x="309.979004" y="18.858999" z="-157.048004"/>
						<normal x="-0.444068" y="0.000000" z="-0.895993"/>
						<texcoord u="0.666700" v="0.000000"/>
					</vertex>
					<vertex>
						<position x="319.105011" y="18.858999" z="-161.570999"/>
						<normal x="-0.444068" y="0.000000" z="-0.895993"/>
						<texcoord u="0.000000" v="0.000000"/>
					</vertex>
					<vertex>
						<position x="-128.703003" y="0.250000" z="-275.835999"/>
						<normal x="-0.976638" y="0.000000" z="-0.214893"/>
						<texcoord u="0.000000" v="1.000000"/>
					</vertex>
					<vertex>
						<position x="-133.115997" y="0.250000" z="-255.779999"/>
						<normal x="-0.976638" y="0.000000" z="-0.214893"/>
						<texcoord u="1.166700" v="1.000000"/>
					</vertex>
					<vertex>
						<position x="-133.115997" y="4.750000" z="-255.779999"/>
						<normal x="-0.976638" y="0.000000" z="-0.214893"/>
						<texcoord u="1.166700" v="0.833400"/>
					</vertex>
					<vertex>
						<position x="-128.703003" y="4.750000" z="-275.835999"/>
						<normal x="-0.976638" y="0.000000" z="-0.214893"/>
						<texcoord u="0.000000" v="0.833400"/>
					</vertex>
					<vertex>
						<position x="-133.115997" y="0.250000" z="-255.779999"/>
						<normal x="-0.976640" y="0.000000" z="-0.214884"/>
						<texcoord u="0.000000" v="1.000000"/>
					</vertex>
					<vertex>
						<position x="-137.529007" y="0.250000" z="-235.723007"/>
						<normal x="-0.976640" y="0.000000" z="-0.214884"/>
						<texcoord u="1.166700" v="1.000000"/>
					</vertex>
					<vertex>
						<position x="-137.529007" y="4.750000" z="-235.723007"/>
						<normal x="-0.976640" y="0.000000" z="-0.214884"/>
						<texcoord u="1.166700" v="0.833400"/>
					</vertex>
					<vertex>
						<position x="-133.115997" y="4.750000" z="-255.779999"/>
						<normal x="-0.976640" y="0.000000" z="-0.214884"/>
						<texcoord u="0.000000" v="0.833400"/>
					</vertex>
					<vertex>
						<position x="-104.500000" y="0.250000" z="-276.699005"/>
						<normal x="-0.035634" y="0.000000" z="-0.999365"/>
						<texcoord u="0.000000" v="1.000000"/>
					</vertex>
					<vertex>
						<position x="-128.703003" y="0.250000" z="-275.835999"/>
						<normal x="-0.035634" y="0.000000" z="-0.999365"/>
						<texcoord u="1.333300" v="1.000000"/>
					</vertex>
					<vertex>
						<position x="-128.703003" y="4.750000" z="-275.835999"/>
						<normal x="-0.035634" y="0.000000" z="-0.999365"/>
						<texcoord u="1.333300" v="0.833400"/>
					</vertex>
					<vertex>
						<position x="-104.500000" y="4.750000" z="-276.699005"/>
						<normal x="-0.035634" y="0.000000" z="-0.999365"/>
						<texcoord u="0.000000" v="0.833400"/>
					</vertex>
					<vertex>
						<position x="-137.529007" y="0.250000" z="-235.723007"/>
						<normal x="0.035588" y="0.000000" z="0.999367"/>
						<texcoord u="0.000000" v="1.000000"/>
					</vertex>
					<vertex>
						<position x="-120.287003" y="0.250000" z="-236.337006"/>
						<normal x="0.035588" y="0.000000" z="0.999367"/>
						<texcoord u="1.000000" v="1.000000"/>
					</vertex>
					<vertex>
						<position x="-120.287003" y="4.750000" z="-236.337006"/>
						<normal x="0.035588" y="0.000000" z="0.999367"/>
						<texcoord u="1.000000" v="0.833400"/>
					</vertex>
					<vertex>
						<position x="-137.529007" y="4.750000" z="-235.723007"/>
						<normal x="0.035588" y="0.000000" z="0.999367"/>
						<texcoord u="0.000000" v="0.833400"/>
					</vertex>
					<vertex>
						<position x="-120.287003" y="0.250000" z="-236.337006"/>
						<normal x="0.035530" y="0.000000" z="0.999369"/>
						<texcoord u="0.000000" v="1.000000"/>
					</vertex>
					<vertex>
						<position x="-103.044998" y="0.250000" z="-236.949997"/>
						<normal x="0.035530" y="0.000000" z="0.999369"/>
						<texcoord u="1.000000" v="1.000000"/>
					</vertex>
					<vertex>
						<position x="-103.044998" y="4.750000" z="-236.949997"/>
						<normal x="0.035530" y="0.000000" z="0.999369"/>
						<texcoord u="1.000000" v="0.833400"/>
					</vertex>
					<vertex>
						<position x="-120.287003" y="4.750000" z="-236.337006"/>
						<normal x="0.035530" y="0.000000" z="0.999369"/>
						<texcoord u="0.000000" v="0.833400"/>
					</vertex>
					<vertex>
						<position x="-133.115997" y="22.427999" z="-255.779999"/>
						<normal x="-0.976638" y="0.000000" z="-0.214893"/>
						<texcoord u="1.166700" v="0.000000"/>
					</vertex>
					<vertex>
						<position x="-128.703003" y="22.427999" z="-275.835999"/>
						<normal x="-0.976638" y="0.000000" z="-0.214893"/>
						<texcoord u="0.000000" v="0.000000"/>
					</vertex>
					<vertex>
						<position x="-137.529007" y="22.427999" z="-235.723007"/>
						<normal x="-0.976640" y="0.000000" z="-0.214884"/>
						<texcoord u="1.166700" v="0.000000"/>
					</vertex>
					<vertex>
						<position x="-133.115997" y="22.427999" z="-255.779999"/>
						<normal x="-0.976640" y="0.000000" z="-0.214884"/>
						<texcoord u="0.000000" v="0.000000"/>
					</vertex>
					<vertex>
						<position x="-128.703003" y="22.427999" z="-275.835999"/>
						<normal x="-0.035634" y="0.000000" z="-0.999365"/>
						<texcoord u="1.333300" v="0.000000"/>
					</vertex>
					<vertex>
						<position x="-104.500000" y="22.427999" z="-276.699005"/>
						<normal x="-0.035634" y="0.000000" z="-0.999365"/>
						<texcoord u="0.000000" v="0.000000"/>
					</vertex>
					<vertex>
						<position x="-120.287003" y="22.427999" z="-236.337006"/>
						<normal x="0.035588" y="0.000000" z="0.999367"/>
						<texcoord u="1.000000" v="0.000000"/>
					</vertex>
					<vertex>
						<position x="-137.529007" y="22.427999" z="-235.723007"/>
						<normal x="0.035588" y="0.000000" z="0.999367"/>
						<texcoord u="0.000000" v="0.000000"/>
					</vertex>
					<vertex>
						<position x="-103.044998" y="22.427999" z="-236.949997"/>
						<normal x="0.035530" y="0.000000" z="0.999369"/>
						<texcoord u="1.000000" v="0.000000"/>
					</vertex>
					<vertex>
						<position x="-120.287003" y="22.427999" z="-236.337006"/>
						<normal x="0.035530" y="0.000000" z="0.999369"/>
						<texcoord u="0.000000" v="0.000000"/>
					</vertex>
					<vertex>
						<position x="391.391998" y="0.250000" z="-311.838013"/>
						<normal x="0.443938" y="0.000000" z="-0.896058"/>
						<texcoord u="0.000000" v="1.000000"/>
					</vertex>
					<vertex>
						<position x="376.276001" y="0.250000" z="-319.326996"/>
						<normal x="0.443938" y="0.000000" z="-0.896058"/>
						<texcoord u="1.000000" v="1.000000"/>
					</vertex>
					<vertex>
						<position x="376.276001" y="4.750000" z="-319.326996"/>
						<normal x="0.443938" y="0.000000" z="-0.896058"/>
						<texcoord u="1.000000" v="0.833400"/>
					</vertex>
					<vertex>
						<position x="391.391998" y="4.750000" z="-311.838013"/>
						<normal x="0.443938" y="0.000000" z="-0.896058"/>
						<texcoord u="0.000000" v="0.833400"/>
					</vertex>
					<vertex>
						<position x="376.276001" y="0.250000" z="-319.326996"/>
						<normal x="0.443915" y="0.000000" z="-0.896069"/>
						<texcoord u="0.000000" v="1.000000"/>
					</vertex>
					<vertex>
						<position x="361.161011" y="0.250000" z="-326.815002"/>
						<normal x="0.443915" y="0.000000" z="-0.896069"/>
						<texcoord u="1.000000" v="1.000000"/>
					</vertex>
					<vertex>
						<position x="361.161011" y="4.750000" z="-326.815002"/>
						<normal x="0.443915" y="0.000000" z="-0.896069"/>
						<texcoord u="1.000000" v="0.833400"/>
					</vertex>
					<vertex>
						<position x="376.276001" y="4.750000" z="-319.326996"/>
						<normal x="0.443915" y="0.000000" z="-0.896069"/>
						<texcoord u="0.000000" v="0.833400"/>
					</vertex>
					<vertex>
						<position x="377.687988" y="0.250000" z="-284.140991"/>
						<normal x="0.896283" y="0.000000" z="0.443482"/>
						<texcoord u="0.000000" v="1.000000"/>
					</vertex>
					<vertex>
						<position x="384.540009" y="0.250000" z="-297.989014"/>
						<normal x="0.896283" y="0.000000" z="0.443482"/>
						<texcoord u="0.833300" v="1.000000"/>
					</vertex>
					<vertex>
						<position x="384.540009" y="4.750000" z="-297.989014"/>
						<normal x="0.896283" y="0.000000" z="0.443482"/>
						<texcoord u="0.833300" v="0.833400"/>
					</vertex>
					<vertex>
						<position x="377.687988" y="4.750000" z="-284.140991"/>
						<normal x="0.896283" y="0.000000" z="0.443482"/>
						<texcoord u="0.000000" v="0.833400"/>
					</vertex>
					<vertex>
						<position x="384.540009" y="0.250000" z="-297.989014"/>
						<normal x="0.896296" y="0.000000" z="0.443455"/>
						<texcoord u="0.000000" v="1.000000"/>
					</vertex>
					<vertex>
						<position x="391.391998" y="0.250000" z="-311.838013"/>
						<normal x="0.896296" y="0.000000" z="0.443455"/>
						<texcoord u="0.833300" v="1.000000"/>
					</vertex>
					<vertex>
						<position x="391.391998" y="4.750000" z="-311.838013"/>
						<normal x="0.896296" y="0.000000" z="0.443455"/>
						<texcoord u="0.833300" v="0.833400"/>
					</vertex>
					<vertex>
						<position x="384.540009" y="4.750000" z="-297.989014"/>
						<normal x="0.896296" y="0.000000" z="0.443455"/>
						<texcoord u="0.000000" v="0.833400"/>
					</vertex>
					<vertex>
						<position x="361.161011" y="0.250000" z="-326.815002"/>
						<normal x="-0.900348" y="0.000000" z="-0.435170"/>
						<texcoord u="0.000000" v="1.000000"/>
					</vertex>
					<vertex>
						<position x="354.359985" y="0.250000" z="-312.743988"/>
						<normal x="-0.900348" y="0.000000" z="-0.435170"/>
						<texcoord u="0.833300" v="1.000000"/>
					</vertex>
					<vertex>
						<position x="354.359985" y="4.750000" z="-312.743988"/>
						<normal x="-0.900348" y="0.000000" z="-0.435170"/>
						<texcoord u="0.833300" v="0.833400"/>
					</vertex>
					<vertex>
						<position x="361.161011" y="4.750000" z="-326.815002"/>
						<normal x="-0.900348" y="0.000000" z="-0.435170"/>
						<texcoord u="0.000000" v="0.833400"/>
					</vertex>
					<vertex>
						<position x="354.359985" y="0.250000" z="-312.743988"/>
						<normal x="-0.900312" y="0.000000" z="-0.435246"/>
						<texcoord u="0.000000" v="1.000000"/>
					</vertex>
					<vertex>
						<position x="347.558014" y="0.250000" z="-298.674011"/>
						<normal x="-0.900312" y="0.000000" z="-0.435246"/>
						<texcoord u="0.833300" v="1.000000"/>
					</vertex>
					<vertex>
						<position x="347.558014" y="4.750000" z="-298.674011"/>
						<normal x="-0.900312" y="0.000000" z="-0.435246"/>
						<texcoord u="0.833300" v="0.833400"/>
					</vertex>
					<vertex>
						<position x="354.359985" y="4.750000" z="-312.743988"/>
						<normal x="-0.900312" y="0.000000" z="-0.435246"/>
						<texcoord u="0.000000" v="0.833400"/>
					</vertex>
					<vertex>
						<position x="376.276001" y="22.427999" z="-319.326996"/>
						<normal x="0.443938" y="0.000000" z="-0.896058"/>
						<texcoord u="1.000000" v="0.000000"/>
					</vertex>
					<vertex>
						<position x="391.391998" y="22.427999" z="-311.838013"/>
						<normal x="0.443938" y="0.000000" z="-0.896058"/>
						<texcoord u="0.000000" v="0.000000"/>
					</vertex>
					<vertex>
						<position x="361.161011" y="22.427999" z="-326.815002"/>
						<normal x="0.443915" y="0.000000" z="-0.896069"/>
						<texcoord u="1.000000" v="0.000000"/>
					</vertex>
					<vertex>
						<position x="376.276001" y="22.427999" z="-319.326996"/>
						<normal x="0.443915" y="0.000000" z="-0.896069"/>
						<texcoord u="0.000000" v="0.000000"/>
					</vertex>
					<vertex>
						<position x="377.687988" y="4.750000" z="-284.140991"/>
						<normal x="0.896283" y="-0.000050" z="0.443482"/>
						<texcoord u="0.000000" v="0.833400"/>
					</vertex>
					<vertex>
						<position x="384.540009" y="4.750000" z="-297.989014"/>
						<normal x="0.896283" y="-0.000050" z="0.443482"/>
						<texcoord u="0.833300" v="0.833400"/>
					</vertex>
					<vertex>
						<position x="384.540985" y="22.427999" z="-297.989014"/>
						<normal x="0.896283" y="-0.000050" z="0.443482"/>
						<texcoord u="0.833300" v="0.000000"/>
					</vertex>
					<vertex>
						<position x="377.688995" y="22.427999" z="-284.140015"/>
						<normal x="0.896283" y="-0.000050" z="0.443482"/>
						<texcoord u="0.000000" v="0.000000"/>
					</vertex>
					<vertex>
						<position x="384.540009" y="4.750000" z="-297.989014"/>
						<normal x="0.896296" y="-0.000076" z="0.443455"/>
						<texcoord u="0.000000" v="0.833400"/>
					</vertex>
					<vertex>
						<position x="391.391998" y="4.750000" z="-311.838013"/>
						<normal x="0.896296" y="-0.000076" z="0.443455"/>
						<texcoord u="0.833300" v="0.833400"/>
					</vertex>
					<vertex>
						<position x="391.393005" y="22.427999" z="-311.837006"/>
						<normal x="0.896296" y="-0.000076" z="0.443455"/>
						<texcoord u="0.833300" v="0.000000"/>
					</vertex>
					<vertex>
						<position x="384.540985" y="22.427999" z="-297.989014"/>
						<normal x="0.896296" y="-0.000076" z="0.443455"/>
						<texcoord u="0.000000" v="0.000000"/>
					</vertex>
					<vertex>
						<position x="354.359985" y="22.427999" z="-312.743988"/>
						<normal x="-0.900348" y="0.000000" z="-0.435170"/>
						<texcoord u="0.833300" v="0.000000"/>
					</vertex>
					<vertex>
						<position x="361.161011" y="22.427999" z="-326.815002"/>
						<normal x="-0.900348" y="0.000000" z="-0.435170"/>
						<texcoord u="0.000000" v="0.000000"/>
					</vertex>
					<vertex>
						<position x="347.558014" y="22.427999" z="-298.674011"/>
						<normal x="-0.900312" y="0.000000" z="-0.435246"/>
						<texcoord u="0.833300" v="0.000000"/>
					</vertex>
					<vertex>
						<position x="354.359985" y="22.427999" z="-312.743988"/>
						<normal x="-0.900312" y="0.000000" z="-0.435246"/>
						<texcoord u="0.000000" v="0.000000"/>
					</vertex>
				</vertexbuffer>
			</geometry>
		</submesh>
	</submeshes>
</mesh>
