<mesh>
	<submeshes>
		<submesh material="RoofTerrasse_2.002" usesharedvertices="false">
			<faces count="16">
				<face v1="0" v2="1" v3="2"/>
				<face v1="0" v2="2" v3="3"/>
				<face v1="4" v2="5" v3="6"/>
				<face v1="4" v2="6" v3="7"/>
				<face v1="8" v2="9" v3="10"/>
				<face v1="8" v2="10" v3="11"/>
				<face v1="12" v2="8" v3="11"/>
				<face v1="13" v2="12" v3="11"/>
				<face v1="14" v2="13" v3="11"/>
				<face v1="14" v2="11" v3="15"/>
				<face v1="16" v2="14" v3="15"/>
				<face v1="17" v2="16" v3="15"/>
				<face v1="18" v2="17" v3="15"/>
				<face v1="19" v2="18" v3="15"/>
				<face v1="20" v2="19" v3="15"/>
				<face v1="21" v2="20" v3="15"/>
			</faces>
			<geometry vertexcount="22">
				<vertexbuffer positions="true" normals="true" texture_coords="1">
					<vertex>
						<position x="36.853001" y="18.462000" z="-425.506989"/>
						<normal x="0.000000" y="1.000000" z="0.000000"/>
						<texcoord u="0.122800" v="1.000000"/>
					</vertex>
					<vertex>
						<position x="16.271999" y="18.462000" z="-427.311005"/>
						<normal x="0.000000" y="1.000000" z="0.000000"/>
						<texcoord u="1.414000" v="1.000000"/>
					</vertex>
					<vertex>
						<position x="15.567000" y="18.462000" z="-396.098999"/>
						<normal x="0.000000" y="1.000000" z="0.000000"/>
						<texcoord u="1.287500" v="-0.947100"/>
					</vertex>
					<vertex>
						<position x="36.209000" y="18.462000" z="-395.670013"/>
						<normal x="0.000000" y="1.000000" z="0.000000"/>
						<texcoord u="0.000000" v="-0.861200"/>
					</vertex>
					<vertex>
						<position x="-108.359001" y="22.855000" z="-368.300995"/>
						<normal x="0.000000" y="1.000000" z="-0.000000"/>
						<texcoord u="0.214600" v="1.000000"/>
					</vertex>
					<vertex>
						<position x="-121.070000" y="22.855000" z="-310.531006"/>
						<normal x="0.000000" y="1.000000" z="-0.000000"/>
						<texcoord u="3.911600" v="1.000000"/>
					</vertex>
					<vertex>
						<position x="-91.818001" y="22.855000" z="-309.859985"/>
						<normal x="0.000000" y="1.000000" z="-0.000000"/>
						<texcoord u="3.559700" v="-0.794500"/>
					</vertex>
					<vertex>
						<position x="-90.538002" y="22.855000" z="-367.895996"/>
						<normal x="0.000000" y="1.000000" z="-0.000000"/>
						<texcoord u="0.000000" v="-0.093200"/>
					</vertex>
					<vertex>
						<position x="369.984985" y="22.982000" z="-116.746002"/>
						<normal x="0.000000" y="1.000000" z="0.000000"/>
						<texcoord u="1.955200" v="0.984200"/>
					</vertex>
					<vertex>
						<position x="368.122986" y="22.982000" z="-117.986000"/>
						<normal x="0.000000" y="1.000000" z="0.000000"/>
						<texcoord u="2.094100" v="1.000000"/>
					</vertex>
					<vertex>
						<position x="368.101013" y="22.982000" z="-117.953003"/>
						<normal x="0.000000" y="1.000000" z="0.000000"/>
						<texcoord u="2.094500" v="0.997500"/>
					</vertex>
					<vertex>
						<position x="377.536011" y="22.982000" z="-111.410004"/>
						<normal x="0.000000" y="1.000000" z="-0.000000"/>
						<texcoord u="1.383100" v="0.903000"/>
					</vertex>
					<vertex>
						<position x="373.692993" y="22.982000" z="-114.373001"/>
						<normal x="0.000000" y="1.000000" z="-0.000000"/>
						<texcoord u="1.681300" v="0.958100"/>
					</vertex>
					<vertex>
						<position x="377.454987" y="22.982000" z="-112.054001"/>
						<normal x="0.000000" y="1.000000" z="-0.000000"/>
						<texcoord u="1.406000" v="0.936500"/>
					</vertex>
					<vertex>
						<position x="381.266998" y="22.982000" z="-109.787003"/>
						<normal x="0.000000" y="1.000000" z="0.000000"/>
						<texcoord u="1.129300" v="0.919200"/>
					</vertex>
					<vertex>
						<position x="363.766998" y="22.982000" z="-51.058998"/>
						<normal x="0.000000" y="1.000000" z="0.000000"/>
						<texcoord u="0.426300" v="-2.845700"/>
					</vertex>
					<vertex>
						<position x="385.125000" y="22.982000" z="-107.567001"/>
						<normal x="0.000000" y="1.000000" z="0.000000"/>
						<texcoord u="0.851400" v="0.905900"/>
					</vertex>
					<vertex>
						<position x="389.027008" y="22.982000" z="-105.391998"/>
						<normal x="0.000000" y="1.000000" z="0.000000"/>
						<texcoord u="0.572400" v="0.896300"/>
					</vertex>
					<vertex>
						<position x="392.967987" y="22.982000" z="-103.259003"/>
						<normal x="0.000000" y="1.000000" z="0.000000"/>
						<texcoord u="0.292400" v="0.890200"/>
					</vertex>
					<vertex>
						<position x="396.946014" y="22.982000" z="-101.165001"/>
						<normal x="0.000000" y="1.000000" z="0.000000"/>
						<texcoord u="0.011400" v="0.887200"/>
					</vertex>
					<vertex>
						<position x="397.065002" y="22.982000" z="-101.102997"/>
						<normal x="0.000000" y="1.000000" z="0.000000"/>
						<texcoord u="0.003000" v="0.887200"/>
					</vertex>
					<vertex>
						<position x="369.835999" y="22.982000" z="-47.944000"/>
						<normal x="0.000000" y="1.000000" z="0.000000"/>
						<texcoord u="0.000000" v="-2.845700"/>
					</vertex>
				</vertexbuffer>
			</geometry>
		</submesh>
	</submeshes>
</mesh>
