<mesh>
	<submeshes>
		<submesh material="BuildGeneric_24" usesharedvertices="false">
			<faces count="20">
				<face v1="0" v2="1" v3="3"/>
				<face v1="1" v2="2" v3="3"/>
				<face v1="4" v2="5" v3="7"/>
				<face v1="5" v2="6" v3="7"/>
				<face v1="8" v2="9" v3="11"/>
				<face v1="9" v2="10" v3="11"/>
				<face v1="12" v2="13" v3="15"/>
				<face v1="13" v2="14" v3="15"/>
				<face v1="16" v2="17" v3="19"/>
				<face v1="17" v2="18" v3="19"/>
				<face v1="3" v2="2" v3="21"/>
				<face v1="2" v2="20" v3="21"/>
				<face v1="7" v2="6" v3="23"/>
				<face v1="6" v2="22" v3="23"/>
				<face v1="11" v2="10" v3="25"/>
				<face v1="10" v2="24" v3="25"/>
				<face v1="15" v2="14" v3="27"/>
				<face v1="14" v2="26" v3="27"/>
				<face v1="19" v2="18" v3="29"/>
				<face v1="18" v2="28" v3="29"/>
			</faces>
			<geometry vertexcount="30">
				<vertexbuffer positions="true" normals="true" texture_coords="1">
					<vertex>
						<position x="-1034.935059" y="-99.750000" z="199.738998"/>
						<normal x="-0.897127" y="0.000000" z="0.441774"/>
						<texcoord u="0.000000" v="1.000000"/>
					</vertex>
					<vertex>
						<position x="-1024.854980" y="-99.750000" z="220.209000"/>
						<normal x="-0.897127" y="0.000000" z="0.441774"/>
						<texcoord u="1.166700" v="1.000000"/>
					</vertex>
					<vertex>
						<position x="-1024.854980" y="-95.250000" z="220.209000"/>
						<normal x="-0.897127" y="0.000000" z="0.441774"/>
						<texcoord u="1.166700" v="0.833400"/>
					</vertex>
					<vertex>
						<position x="-1034.935059" y="-95.250000" z="199.738998"/>
						<normal x="-0.897127" y="0.000000" z="0.441774"/>
						<texcoord u="0.000000" v="0.833400"/>
					</vertex>
					<vertex>
						<position x="-1024.854980" y="-99.750000" z="220.209000"/>
						<normal x="-0.897154" y="0.000000" z="0.441718"/>
						<texcoord u="0.000000" v="1.000000"/>
					</vertex>
					<vertex>
						<position x="-1014.776001" y="-99.750000" z="240.679993"/>
						<normal x="-0.897154" y="0.000000" z="0.441718"/>
						<texcoord u="1.166700" v="1.000000"/>
					</vertex>
					<vertex>
						<position x="-1014.776001" y="-95.250000" z="240.679993"/>
						<normal x="-0.897154" y="0.000000" z="0.441718"/>
						<texcoord u="1.166700" v="0.833400"/>
					</vertex>
					<vertex>
						<position x="-1024.854980" y="-95.250000" z="220.209000"/>
						<normal x="-0.897154" y="0.000000" z="0.441718"/>
						<texcoord u="0.000000" v="0.833400"/>
					</vertex>
					<vertex>
						<position x="-1013.822021" y="-99.750000" z="192.500000"/>
						<normal x="-0.186076" y="0.000000" z="-0.982535"/>
						<texcoord u="0.000000" v="1.000000"/>
					</vertex>
					<vertex>
						<position x="-1033.147949" y="-99.750000" z="196.160004"/>
						<normal x="-0.186076" y="0.000000" z="-0.982535"/>
						<texcoord u="1.000000" v="1.000000"/>
					</vertex>
					<vertex>
						<position x="-1033.147949" y="-95.250000" z="196.160004"/>
						<normal x="-0.186076" y="0.000000" z="-0.982535"/>
						<texcoord u="1.000000" v="0.833400"/>
					</vertex>
					<vertex>
						<position x="-1013.822021" y="-95.250000" z="192.500000"/>
						<normal x="-0.186076" y="0.000000" z="-0.982535"/>
						<texcoord u="0.000000" v="0.833400"/>
					</vertex>
					<vertex>
						<position x="-1033.147949" y="-99.750000" z="196.160004"/>
						<normal x="-0.894666" y="0.000000" z="-0.446736"/>
						<texcoord u="0.000000" v="1.000000"/>
					</vertex>
					<vertex>
						<position x="-1034.935059" y="-99.750000" z="199.738998"/>
						<normal x="-0.894666" y="0.000000" z="-0.446736"/>
						<texcoord u="0.333300" v="1.000000"/>
					</vertex>
					<vertex>
						<position x="-1034.935059" y="-95.250000" z="199.738998"/>
						<normal x="-0.894666" y="0.000000" z="-0.446736"/>
						<texcoord u="0.333300" v="0.833400"/>
					</vertex>
					<vertex>
						<position x="-1033.147949" y="-95.250000" z="196.160004"/>
						<normal x="-0.894666" y="0.000000" z="-0.446736"/>
						<texcoord u="0.000000" v="0.833400"/>
					</vertex>
					<vertex>
						<position x="-1014.776001" y="-99.750000" z="240.679993"/>
						<normal x="0.442821" y="0.000000" z="0.896610"/>
						<texcoord u="0.000000" v="1.000000"/>
					</vertex>
					<vertex>
						<position x="-994.911011" y="-99.750000" z="230.869003"/>
						<normal x="0.442821" y="0.000000" z="0.896610"/>
						<texcoord u="1.166700" v="1.000000"/>
					</vertex>
					<vertex>
						<position x="-994.911011" y="-95.250000" z="230.869003"/>
						<normal x="0.442821" y="0.000000" z="0.896610"/>
						<texcoord u="1.166700" v="0.833400"/>
					</vertex>
					<vertex>
						<position x="-1014.776001" y="-95.250000" z="240.679993"/>
						<normal x="0.442821" y="0.000000" z="0.896610"/>
						<texcoord u="0.000000" v="0.833400"/>
					</vertex>
					<vertex>
						<position x="-1024.854980" y="-80.570999" z="220.209000"/>
						<normal x="-0.897127" y="0.000000" z="0.441774"/>
						<texcoord u="1.166700" v="0.000000"/>
					</vertex>
					<vertex>
						<position x="-1034.935059" y="-80.570999" z="199.738998"/>
						<normal x="-0.897127" y="0.000000" z="0.441774"/>
						<texcoord u="0.000000" v="0.000000"/>
					</vertex>
					<vertex>
						<position x="-1014.776001" y="-80.570999" z="240.679993"/>
						<normal x="-0.897154" y="0.000000" z="0.441718"/>
						<texcoord u="1.166700" v="0.000000"/>
					</vertex>
					<vertex>
						<position x="-1024.854980" y="-80.570999" z="220.209000"/>
						<normal x="-0.897154" y="0.000000" z="0.441718"/>
						<texcoord u="0.000000" v="0.000000"/>
					</vertex>
					<vertex>
						<position x="-1033.147949" y="-80.570999" z="196.160004"/>
						<normal x="-0.186076" y="0.000000" z="-0.982535"/>
						<texcoord u="1.000000" v="0.000000"/>
					</vertex>
					<vertex>
						<position x="-1013.822021" y="-80.570999" z="192.500000"/>
						<normal x="-0.186076" y="0.000000" z="-0.982535"/>
						<texcoord u="0.000000" v="0.000000"/>
					</vertex>
					<vertex>
						<position x="-1034.935059" y="-80.570999" z="199.738998"/>
						<normal x="-0.894666" y="0.000000" z="-0.446736"/>
						<texcoord u="0.333300" v="0.000000"/>
					</vertex>
					<vertex>
						<position x="-1033.147949" y="-80.570999" z="196.160004"/>
						<normal x="-0.894666" y="0.000000" z="-0.446736"/>
						<texcoord u="0.000000" v="0.000000"/>
					</vertex>
					<vertex>
						<position x="-994.911011" y="-80.570999" z="230.869003"/>
						<normal x="0.442821" y="0.000000" z="0.896610"/>
						<texcoord u="1.166700" v="0.000000"/>
					</vertex>
					<vertex>
						<position x="-1014.776001" y="-80.570999" z="240.679993"/>
						<normal x="0.442821" y="0.000000" z="0.896610"/>
						<texcoord u="0.000000" v="0.000000"/>
					</vertex>
				</vertexbuffer>
			</geometry>
		</submesh>
	</submeshes>
</mesh>
